barneySA/__init__.py
barneySA/tools.py
barneySA-1.0.1.dist-info/METADATA
barneySA-1.0.1.dist-info/WHEEL
barneySA-1.0.1.dist-info/top_level.txt
barneySA-1.0.1.dist-info/RECORD
