Metadata-Version: 2.1
Name: barneySA
Version: 1.0.1
Summary: A general-purpose sensitivity analsysi library based on fractional factorial design and the analysis of variance
Home-page: https://github.com/janursa/barneySA
Author: Jalil Nourisa
Author-email: jalil.nourisa@gmail.com
License: UNKNOWN
Platform: UNKNOWN
Classifier: Programming Language :: Python :: 3
Classifier: Operating System :: OS Independent
Requires-Python: >=3.6
Requires-Dist: numpy (>=1.18.4)
Requires-Dist: mpi4py (>=3.0.3)
Requires-Dist: doepy (>=0.0.1)
